<annotation>
<folder>image_download_folder</folder>
<filename>county_player_36.jpg</filename>
<path>image_download_folder\county_player_36.jpg</path>
<source>
	<database>Unknown</database>
</source>
<size>
	<width>280</width>
	<height>440</height>
	<depth>Unspecified</depth>
</size>
<segmented>Unspecified</segmented>
<object>
	<name>ball</name>
	<pose>Unspecified</pose>
	<truncated>Unspecified</truncated>
	<difficult>Unspecified</difficult>
	<occluded>Unspecified</occluded>
	<bndbox>
		<xmin>17.0</xmin>
		<xmax>250.0</xmax>
		<ymin>10.0</ymin>
		<ymax>435.0</ymax>
	</bndbox>
</object>
<object>
	<name>ball</name>
	<pose>Unspecified</pose>
	<truncated>Unspecified</truncated>
	<difficult>Unspecified</difficult>
	<occluded>Unspecified</occluded>
	<bndbox>
		<xmin>120.0</xmin>
		<xmax>216.0</xmax>
		<ymin>223.0</ymin>
		<ymax>331.0</ymax>
	</bndbox>
</object>
</annotation>